documentextractor/__init__.py
documentextractor/client.py
documentextractor/exceptions.py
documentextractor-0.5.2.dist-info/LICENSE
documentextractor-0.5.2.dist-info/METADATA
documentextractor-0.5.2.dist-info/WHEEL
documentextractor-0.5.2.dist-info/top_level.txt
documentextractor-0.5.2.dist-info/RECORD
