Metadata-Version: 2.1
Name: documentextractor
Version: 0.5.2
Summary: The official Python client for the DocumentExtractor API
Home-page: https://github.com/procentriq-hq/documentextractor-client-python
Author: Philipp Heller
Author-email: philipp@documentextractor.ai
License: Apache-2.0
Platform: UNKNOWN
Classifier: Programming Language :: Python :: 3
Classifier: License :: OSI Approved :: Apache Software License
Classifier: Operating System :: OS Independent
Requires-Python: >=3.8
Requires-Dist: requests>=2.25.0
Requires-Dist: pydantic>=2.0
Requires-Dist: documentextractor-commons>=0.4.4
